enmity/__init__.py
enmity/__main__.py
enmity/bot.py
enmity/colors.py
enmity/components.py
enmity/embeds.py
enmity/intents.py
enmity/interactions.py
enmity/messages.py
enmity/opcodes.py
enmity/users.py
enmity-0.2.0.dist-info/LICENSE
enmity-0.2.0.dist-info/METADATA
enmity-0.2.0.dist-info/WHEEL
enmity-0.2.0.dist-info/top_level.txt
enmity-0.2.0.dist-info/RECORD
